sfc_models/__init__.py
sfc_models/base_solver.py
sfc_models/equation.py
sfc_models/equation_parser.py
sfc_models/equation_solver.py
sfc_models/external.py
sfc_models/models.py
sfc_models/objects.py
sfc_models/sector.py
sfc_models/sector_definitions.py
sfc_models/utils.py
sfc_models/examples/Quick2DPlot.py
sfc_models/examples/__init__.py
sfc_models/examples/install_example_scripts.py
sfc_models/examples/install_examples.py
sfc_models/examples/scripts/SIM_Model_With_Capitalists.py
sfc_models/examples/scripts/__init__.py
sfc_models/examples/scripts/build_SIM_model.py
sfc_models/examples/scripts/build_run_all_scripts.py
sfc_models/examples/scripts/build_script_list.py
sfc_models/examples/scripts/ex20161103_SIM_2_country.py
sfc_models/examples/scripts/ex20161128_tax_cut_comparison.py
sfc_models/examples/scripts/ex20161206_SIM_with_deposits.py
sfc_models/examples/scripts/ex20170221_Model_PC.py
sfc_models/examples/scripts/ex20170225_Model_REG.py
sfc_models/examples/scripts/ex20170307_Model_REG2.py
sfc_models/examples/scripts/ex20171127_equations_state_space_models.py
sfc_models/examples/scripts/ex20190131_investment_accelerator.py
sfc_models/examples/scripts/ex20190324_consumption_propensity.py
sfc_models/examples/scripts/ex201904110_accelerator_gummint.py
sfc_models/examples/scripts/ex20190412_oscillate_wildly.py
sfc_models/examples/scripts/intro_3_02_example.py
sfc_models/examples/scripts/intro_3_03_hello_world_1.py
sfc_models/examples/scripts/intro_3_03_hello_world_2.py
sfc_models/examples/scripts/intro_3_03_hello_world_3.py
sfc_models/examples/scripts/intro_3_03_hello_world_4.py
sfc_models/examples/scripts/intro_3_05_variable_names_1.py
sfc_models/examples/scripts/intro_3_05_variable_names_2.py
sfc_models/examples/scripts/intro_5_03_no_tax_SIM.py
sfc_models/examples/scripts/intro_5_04_SIMEX1.py
sfc_models/examples/scripts/intro_6_04_externalsector.py
sfc_models/examples/scripts/intro_6_06_gold_standard_G.py
sfc_models/examples/scripts/intro_X_XX_sim_fiscal.py
sfc_models-1.0.3.dist-info/LICENSE
sfc_models-1.0.3.dist-info/METADATA
sfc_models-1.0.3.dist-info/WHEEL
sfc_models-1.0.3.dist-info/top_level.txt
sfc_models-1.0.3.dist-info/RECORD
