Metadata-Version: 2.1
Name: sfc-models
Version: 1.0.3
Summary: Stock-Flow Consistent (SFC) model generation
Home-page: https://github.com/brianr747/SFC_models
Author: Brian Romanchuk
Author-email: brianr747@gmail.com
License: UNKNOWN
Keywords: economics,SFC models,stock-flow consistent models
Platform: UNKNOWN
Classifier: Development Status :: 4 - Beta
Classifier: Intended Audience :: Science/Research
Classifier: License :: OSI Approved :: Apache Software License
Classifier: Natural Language :: English
Classifier: Operating System :: OS Independent
Classifier: Programming Language :: Python
Classifier: Programming Language :: Python :: 2
Classifier: Programming Language :: Python :: 2.7
Classifier: Programming Language :: Python :: 3
Classifier: Programming Language :: Python :: 3.0
Classifier: Programming Language :: Python :: 3.1
Classifier: Programming Language :: Python :: 3.2
Classifier: Programming Language :: Python :: 3.3
Classifier: Programming Language :: Python :: 3.4
Classifier: Programming Language :: Python :: 3.5
Classifier: Programming Language :: Python :: 3.6
Classifier: Topic :: Other/Nonlisted Topic
Provides-Extra: charts
Requires-Dist: matplotlib (>=2.0) ; extra == 'charts'
